imem.v
module IMem(
        output wire [15:0] data,
        input [3:0] a);

    reg [15:0] ram [0:31];

    //initial $readmemh("fibb_iter.txt", ram); // load file with instructions onto memory
    //initial $readmemh("I-type_test.txt", ram);
    //initial $readmemh("R-type-test.txt", ram);
    //initial $readmemh("D-type-test.txt", ram);
    initial $readmemh("J-type-test.txt", ram);

    assign data = ram[a];

endmodule

RAM.v
module RAM(
        inout [15:0] data,
        input [3:0] addr,
        input we, clk, oe
        );

    reg [15:0] ram [15:0];
    reg [15:0] tmp_data;

    always @ (posedge clk)
    begin
        if(we)
            ram[addr] <= data;  
        else
            tmp_data <= data;
    end

    assign data = oe & !we ? tmp_data : 'hz;

endmodule

buffer.v
module buffer(input [15:0] in, 
              input en, clk,
              output reg [15:0] out);
    
    always @(*) begin
        if(en)
            out <= in;
        else
            out <= 16'bx; // high impedence output to not interfere with bus
    end

endmodule

alu.v
module alu(
           input [15:0] A,B,  // ALU 8-bit Inputs                 
           input [2:0] ALU_Sel,// ALU Selection
           input shamt,
           output [15:0] ALU_Out, // ALU 8-bit Output
           output CarryOut // Carry Out Flag
    );
    reg [15:0] ALU_Result;
    wire [16:0] tmp;
    assign ALU_Out = ALU_Result; // ALU out
    assign tmp = {1'b0,A} + {1'b0,B};
    assign CarryOut = tmp[16]; // Carryout flag

    always @(*)
    begin
        case(ALU_Sel)
          3'b000: // Addition
           ALU_Result = A + B ; 
          3'b001: // Subtraction
           ALU_Result = A - B ;
          3'b010: //  Logical and 
           ALU_Result = A & B;
          3'b011: //  Logical or
           ALU_Result = A | B;
          3'b100: //  Logical xor 
           ALU_Result = A ^ B;
          3'b101: //  Logical nor
           ALU_Result = ~(A | B);
          3'b110: // Logical nand 
           ALU_Result = ~(A & B);
          3'b111: // LSL
           ALU_Result = A<<shamt;
          default: ALU_Result = A + B; 
        endcase
    end
endmodule

CPU.v
module CPU();

    //instruction 15-12 11-8 7-4 3-0

    reg [15:0] instruction;
    reg [15:0] A, B, zero;
    reg [15:0] Rx [15:0];
    reg [2:0] alu_sel;
    reg [3:0] addr, shamt, a, pc;
    reg en_alu, en_imem, we, oe, clk;
    wire [15:0] bus, ins_bus;
    wire carryFlag;
    wire [3:0] Rn, Rd, Rm, opcode;
   
    integer i;

    assign opcode = instruction[15:12];
    assign Rd = instruction[11:8];
    assign Rn = instruction[7:4];
    assign Rm = instruction[3:0];

    wire [15:0] tmp_alu;
    alu aluop(.A(A), .B(B), .ALU_Out(tmp_alu), .ALU_Sel(alu_sel), .CarryOut(carryFlag), .shamt(shamt));
    buffer aluBuff(.clk(clk), .en(en_alu), .in(tmp_alu), .out(bus));
    RAM data(.data(bus), .clk(clk), .we(we), .oe(oe), .addr(addr));
    IMem mem(.a(pc), .data(ins_bus));
    
    always@(posedge clk)
    begin
        case(opcode)
            4'h0:begin      // ADD
                A <= Rx[Rn];
                B <= Rx[Rm];
                alu_sel = 3'b000;
                en_alu = 1'b1;
                #1
                Rx[Rd] = bus;
                en_alu = 1'b0;
            end
            4'h1:begin      // ADDI
                A <= Rx[Rn];
                B <= Rm;
                alu_sel = 3'b000;
                en_alu = 1'b1;
                #1
                Rx[Rd] = bus;
                en_alu = 1'b0;
            end
            4'h2:begin      // SUB
                A <= Rx[Rn];
                B <= Rx[Rm];
                alu_sel = 3'b001;
                en_alu = 1'b1;
                #1
                Rx[Rd] = bus;
                en_alu = 1'b0;
            end
            4'h3:begin      //SUBI
                A <= Rx[Rn];
                B <= Rm;
                alu_sel = 3'b001;
                en_alu = 1'b1;
                #1
                Rx[Rd] = bus;
                en_alu = 1'b0;
            end
            4'h4:begin      //AND
                A <= Rx[Rn];
                B <= Rx[Rm];
                alu_sel = 3'b010;
                en_alu = 1'b1;
                #1
                Rx[Rd] = bus;
                en_alu = 1'b0;
            end
            4'h5:begin      //OR
                A <= Rx[Rn];
                B <= Rx[Rm];
                alu_sel = 3'b011;
                en_alu = 1'b1;
                #1
                Rx[Rd] = bus;
                en_alu = 1'b0;
            end
            4'h6:begin      //XOR
                A <= Rx[Rn];
                B <= Rx[Rm];
                alu_sel = 3'b100;
                en_alu = 1'b1;
                #1
                Rx[Rd] = bus;
                en_alu = 1'b0;
            end
            4'h7:begin      //Display
                $display("%d", Rx[Rd]);
            end
            4'h8:begin      //NAND
                A <= Rx[Rn];
                B <= Rx[Rm];
                alu_sel = 3'b110;
                en_alu = 1'b1;
                #1
                Rx[Rd] = bus;
                en_alu = 1'b0;
            end
            4'h9: $finish;
            4'ha:begin      //LSL
                A <= Rx[Rn];
                shamt <= Rm;
                alu_sel = 3'b111;
                en_alu = 1'b1;
                #1
                Rx[Rd] = bus;
                en_alu = 1'b0;
            end
            4'hb:begin      //BL
                Rx[15] = pc + 1;
                pc = Rx[Rd]-1;
            end
            4'hc:begin      //BEQ (to immediate)
                if(Rx[Rn] == Rx[Rm]) begin
                    pc = Rx[Rd]-1;
                end
            end
            4'hd:begin      //branch to register
                pc = Rx[Rd]-1;
            end
            4'he:begin      //STUR because of the way the registers were implemented, I have to get them onto the bus using the alu
                addr = Rd;
                A <= 0;
                B <= Rx[Rn];
                alu_sel = 'b000;
                en_alu = 1;
                oe = 0;
                we = 1;
                #1
                we = 0;
                en_alu = 0;
            end
            4'hf:begin      //LDUR
                addr = Rd;
                we = 0;
                oe = 1;
                Rx[Rn] = bus;
                oe = 0;
            end
            default : A = 4'hz; //dummy code so it compiles
        endcase
    end

    always @(negedge clk)
    begin
        pc = pc + 1;
        #10
        instruction = ins_bus;
    end

    always #500 clk = ~clk;

    //instruction opcode, rd, rn, rm

    initial begin
        clk = 0;
        {we, oe, en_alu, addr, a, en_imem, zero} <= 0;
        for(i = 0; i < 16; i = i+1) begin
            Rx[i] = 0;
        end
        i = 0;
        pc = -1;
        #100
        $dumpfile("test.vcd");
        $dumpvars(0, clk, instruction, bus);
        //$monitor("%d",Rx[1]);
        
    end
endmodule

test.vcd
$date
	Thu Apr 28 14:04:26 2022
$end
$version
	Icarus Verilog
$end
$timescale
	1s
$end
$scope module CPU $end
$var reg 1 ! clk $end
$upscope $end
$scope module CPU $end
$var reg 16 " instruction [15:0] $end
$upscope $end
$scope module CPU $end
$var wire 16 # bus [15:0] $end
$upscope $end
$enddefinitions $end
#100
$dumpvars
bz #
b1000011100000 "
0!
$end
#500
b0 #
1!
#501
bz #
#1000
0!
#1010
b1000111100001 "
#1500
b1 #
1!
#1501
bz #
#2000
0!
#2010
b1010011101111 "
#2500
b1111 #
1!
#2501
bz #
#3000
0!
#3010
b1001111100001 "
#3500
b1 #
1!
#3501
bz #
#4000
0!
#4010
b1010111101100 "
#4500
b1100 #
1!
#4501
bz #
#5000
0!
#5010
b1011011100110 "
#5500
b110 #
1!
#5501
bz #
#6000
0!
#6010
b1000010000 "
#6500
b1 #
1!
#6501
bz #
#7000
0!
#7010
b1000000010000 "
#7500
b1 #
1!
#7501
bz #
#8000
0!
#8010
b1000100100000 "
#8500
b1 #
1!
#8501
bz #
#9000
0!
#9010
b1001100110001 "
#9500
b10 #
1!
#9501
bz #
#10000
0!
#10010
b1100010100110100 "
#10500
1!
#11000
0!
#11010
b1101011000000000 "
#11500
1!
#12000
0!
#12010
b1000010000 "
#12500
b10 #
1!
#12501
bz #
#13000
0!
#13010
b1000000010000 "
#13500
b1 #
1!
#13501
bz #
#14000
0!
#14010
b1000100100000 "
#14500
b10 #
1!
#14501
bz #
#15000
0!
#15010
b1001100110001 "
#15500
b11 #
1!
#15501
bz #
#16000
0!
#16010
b1100010100110100 "
#16500
1!
#17000
0!
#17010
b1101011000000000 "
#17500
1!
#18000
0!
#18010
b1000010000 "
#18500
b11 #
1!
#18501
bz #
#19000
0!
#19010
b1000000010000 "
#19500
b10 #
1!
#19501
bz #
#20000
0!
#20010
b1000100100000 "
#20500
b11 #
1!
#20501
bz #
#21000
0!
#21010
b1001100110001 "
#21500
b100 #
1!
#21501
bz #
#22000
0!
#22010
b1100010100110100 "
#22500
1!
#23000
0!
#23010
b1101011000000000 "
#23500
1!
#24000
0!
#24010
b1000010000 "
#24500
b101 #
1!
#24501
bz #
#25000
0!
#25010
b1000000010000 "
#25500
b11 #
1!
#25501
bz #
#26000
0!
#26010
b1000100100000 "
#26500
b101 #
1!
#26501
bz #
#27000
0!
#27010
b1001100110001 "
#27500
b101 #
1!
#27501
bz #
#28000
0!
#28010
b1100010100110100 "
#28500
1!
#29000
0!
#29010
b1101011000000000 "
#29500
1!
#30000
0!
#30010
b1000010000 "
#30500
b1000 #
1!
#30501
bz #
#31000
0!
#31010
b1000000010000 "
#31500
b101 #
1!
#31501
bz #
#32000
0!
#32010
b1000100100000 "
#32500
b1000 #
1!
#32501
bz #
#33000
0!
#33010
b1001100110001 "
#33500
b110 #
1!
#33501
bz #
#34000
0!
#34010
b1100010100110100 "
#34500
1!
#35000
0!
#35010
b1101011000000000 "
#35500
1!
#36000
0!
#36010
b1000010000 "
#36500
b1101 #
1!
#36501
bz #
#37000
0!
#37010
b1000000010000 "
#37500
b1000 #
1!
#37501
bz #
#38000
0!
#38010
b1000100100000 "
#38500
b1101 #
1!
#38501
bz #
#39000
0!
#39010
b1001100110001 "
#39500
b111 #
1!
#39501
bz #
#40000
0!
#40010
b1100010100110100 "
#40500
1!
#41000
0!
#41010
b1101011000000000 "
#41500
1!
#42000
0!
#42010
b1000010000 "
#42500
b10101 #
1!
#42501
bz #
#43000
0!
#43010
b1000000010000 "
#43500
b1101 #
1!
#43501
bz #
#44000
0!
#44010
b1000100100000 "
#44500
b10101 #
1!
#44501
bz #
#45000
0!
#45010
b1001100110001 "
#45500
b1000 #
1!
#45501
bz #
#46000
0!
#46010
b1100010100110100 "
#46500
1!
#47000
0!
#47010
b1101011000000000 "
#47500
1!
#48000
0!
#48010
b1000010000 "
#48500
b100010 #
1!
#48501
bz #
#49000
0!
#49010
b1000000010000 "
#49500
b10101 #
1!
#49501
bz #
#50000
0!
#50010
b1000100100000 "
#50500
b100010 #
1!
#50501
bz #
#51000
0!
#51010
b1001100110001 "
#51500
b1001 #
1!
#51501
bz #
#52000
0!
#52010
b1100010100110100 "
#52500
1!
#53000
0!
#53010
b1101011000000000 "
#53500
1!
#54000
0!
#54010
b1000010000 "
#54500
b110111 #
1!
#54501
bz #
#55000
0!
#55010
b1000000010000 "
#55500
b100010 #
1!
#55501
bz #
#56000
0!
#56010
b1000100100000 "
#56500
b110111 #
1!
#56501
bz #
#57000
0!
#57010
b1001100110001 "
#57500
b1010 #
1!
#57501
bz #
#58000
0!
#58010
b1100010100110100 "
#58500
1!
#59000
0!
#59010
b1101011000000000 "
#59500
1!
#60000
0!
#60010
b1000010000 "
#60500
b1011001 #
1!
#60501
bz #
#61000
0!
#61010
b1000000010000 "
#61500
b110111 #
1!
#61501
bz #
#62000
0!
#62010
b1000100100000 "
#62500
b1011001 #
1!
#62501
bz #
#63000
0!
#63010
b1001100110001 "
#63500
b1011 #
1!
#63501
bz #
#64000
0!
#64010
b1100010100110100 "
#64500
1!
#65000
0!
#65010
b1101011000000000 "
#65500
1!
#66000
0!
#66010
b1000010000 "
#66500
b10010000 #
1!
#66501
bz #
#67000
0!
#67010
b1000000010000 "
#67500
b1011001 #
1!
#67501
bz #
#68000
0!
#68010
b1000100100000 "
#68500
b10010000 #
1!
#68501
bz #
#69000
0!
#69010
b1001100110001 "
#69500
b1100 #
1!
#69501
bz #
#70000
0!
#70010
b1100010100110100 "
#70500
1!
#71000
0!
#71010
b1101011000000000 "
#71500
1!
#72000
0!
#72010
b1000010000 "
#72500
b11101001 #
1!
#72501
bz #
#73000
0!
#73010
b1000000010000 "
#73500
b10010000 #
1!
#73501
bz #
#74000
0!
#74010
b1000100100000 "
#74500
b11101001 #
1!
#74501
bz #
#75000
0!
#75010
b1001100110001 "
#75500
b1101 #
1!
#75501
bz #
#76000
0!
#76010
b1100010100110100 "
#76500
1!
#77000
0!
#77010
b1101011000000000 "
#77500
1!
#78000
0!
#78010
b1000010000 "
#78500
b101111001 #
1!
#78501
bz #
#79000
0!
#79010
b1000000010000 "
#79500
b11101001 #
1!
#79501
bz #
#80000
0!
#80010
b1000100100000 "
#80500
b101111001 #
1!
#80501
bz #
#81000
0!
#81010
b1001100110001 "
#81500
b1110 #
1!
#81501
bz #
#82000
0!
#82010
b1100010100110100 "
#82500
1!
#83000
0!
#83010
b1101011000000000 "
#83500
1!
#84000
0!
#84010
b1000010000 "
#84500
b1001100010 #
1!
#84501
bz #
#85000
0!
#85010
b1000000010000 "
#85500
b101111001 #
1!
#85501
bz #
#86000
0!
#86010
b1000100100000 "
#86500
b1001100010 #
1!
#86501
bz #
#87000
0!
#87010
b1001100110001 "
#87500
b1111 #
1!
#87501
bz #
#88000
0!
#88010
b1100010100110100 "
#88500
1!
#89000
0!
#89010
b111000100000000 "
#89500
1!
#90000
0!
#90010
b1001000000000000 "
