imem.v
module IMem(
        output wire [15:0] data,
        input [3:0] a);

    reg [15:0] ram [0:31];

    //initial $readmemh("fibb_iter.txt", ram); // load file with instructions onto memory
    //initial $readmemh("I-type_test.txt", ram);
    //initial $readmemh("R-type-test.txt", ram);
    //initial $readmemh("D-type-test.txt", ram);
    initial $readmemh("J-type-test.txt", ram);

    assign data = ram[a];

endmodule

RAM.v
module RAM(
        inout [15:0] data,
        input [3:0] addr,
        input we, clk, oe
        );

    reg [15:0] ram [15:0];
    reg [15:0] tmp_data;

    always @ (posedge clk)
    begin
        if(we)
            ram[addr] <= data;  
        else
            tmp_data <= data;
    end

    assign data = oe & !we ? tmp_data : 'hz;

endmodule

buffer.v
module buffer(input [15:0] in, 
              input en, clk,
              output reg [15:0] out);
    
    always @(*) begin
        if(en)
            out <= in;
        else
            out <= 16'bx; // high impedence output to not interfere with bus
    end

endmodule

alu.v
module alu(
           input [15:0] A,B,  // ALU 8-bit Inputs                 
           input [2:0] ALU_Sel,// ALU Selection
           input shamt,
           output [15:0] ALU_Out, // ALU 8-bit Output
           output CarryOut // Carry Out Flag
    );
    reg [15:0] ALU_Result;
    wire [16:0] tmp;
    assign ALU_Out = ALU_Result; // ALU out
    assign tmp = {1'b0,A} + {1'b0,B};
    assign CarryOut = tmp[16]; // Carryout flag

    always @(*)
    begin
        case(ALU_Sel)
          3'b000: // Addition
           ALU_Result = A + B ; 
          3'b001: // Subtraction
           ALU_Result = A - B ;
          3'b010: //  Logical and 
           ALU_Result = A & B;
          3'b011: //  Logical or
           ALU_Result = A | B;
          3'b100: //  Logical xor 
           ALU_Result = A ^ B;
          3'b101: //  Logical nor
           ALU_Result = ~(A | B);
          3'b110: // Logical nand 
           ALU_Result = ~(A & B);
          3'b111: // LSL
           ALU_Result = A<<shamt;
          default: ALU_Result = A + B; 
        endcase
    end
endmodule

CPU.v
module CPU();

    //instruction 15-12 11-8 7-4 3-0

    reg [15:0] instruction, C;
    reg [15:0] A, B;
    reg [15:0] Rx [15:0];
    reg [2:0] alu_sel;
    wire [15:0] bus;
    wire carryFlag;
    reg en_alu, en_imem, shamt;
    wire [3:0] Rn, Rd, Rm, opcode;
    reg clk;
    reg we, oe;
    reg [3:0] addr;
    reg [3:0] a, pc;
    integer i;

    assign opcode = instruction[15:12];
    assign Rd = instruction[11:8];
    assign Rn = instruction[7:4];
    assign Rm = instruction[3:0];

    wire [15:0] tmp_alu, tmp_mem;
    alu aluop(.A(A), .B(B), .ALU_Out(tmp_alu), .ALU_Sel(alu_sel), .CarryOut(carryFlag), .shamt(shamt));
    buffer aluBuff(.clk(clk), .en(en_alu), .in(tmp_alu), .out(bus));
    RAM data(.data(bus), .clk(clk), .we(we), .oe(oe), .addr(addr));
    IMem mem(.a(pc), .data(tmp_mem));
    
    always@(posedge clk)
    begin
        case(opcode)
            4'h0:begin      // ADD
                A <= Rx[Rn];
                B <= Rx[Rm];
                alu_sel = 3'b000;
                en_alu = 1'b1;
                #1
                Rx[Rd] = bus;
                en_alu = 1'b0;
            end
            4'h1:begin      // ADDI
                A <= Rx[Rn];
                B <= Rm;
                alu_sel = 3'b000;
                en_alu = 1'b1;
                #1
                Rx[Rd] = bus;
                en_alu = 1'b0;
            end
            4'h2:begin      // SUB
                A <= Rx[Rn];
                B <= Rx[Rm];
                alu_sel = 3'b001;
                en_alu = 1'b1;
                #1
                Rx[Rd] = bus;
                en_alu = 1'b0;
            end
            4'h3:begin      //SUBI
                A <= Rx[Rn];
                B <= Rm;
                alu_sel = 3'b001;
                en_alu = 1'b1;
                #1
                Rx[Rd] = bus;
                en_alu = 1'b0;
            end
            4'h4:begin      //AND
                A <= Rx[Rn];
                B <= Rx[Rm];
                alu_sel = 3'b010;
                en_alu = 1'b1;
                #1
                Rx[Rd] = bus;
                en_alu = 1'b0;
            end
            4'h5:begin      //OR
                A <= Rx[Rn];
                B <= Rx[Rm];
                alu_sel = 3'b011;
                en_alu = 1'b1;
                #1
                Rx[Rd] = bus;
                en_alu = 1'b0;
            end
            4'h6:begin      //XOR
                A <= Rx[Rn];
                B <= Rx[Rm];
                alu_sel = 3'b100;
                en_alu = 1'b1;
                #1
                Rx[Rd] = bus;
                en_alu = 1'b0;
            end
            4'h7:begin      //NOR
                A <= Rx[Rn];
                B <= Rx[Rm];
                alu_sel = 3'b101;
                en_alu = 1'b1;
                #1
                Rx[Rd] = bus;
                en_alu = 1'b0;
            end
            4'h8:begin      //NAND
                A <= Rx[Rn];
                B <= Rx[Rm];
                alu_sel = 3'b110;
                en_alu = 1'b1;
                #1
                Rx[Rd] = bus;
                en_alu = 1'b0;
            end
            4'h9: $finish;
            4'ha:begin      //LSL
                A <= Rx[Rn];
                shamt <= Rm;
                alu_sel = 3'b111;
                en_alu = 1'b1;
                #1
                Rx[Rd] = bus;
                en_alu = 1'b0;
            end
            4'hc:begin      //BEQ (to immediate)
                if(Rx[Rn] == Rm) begin
                    pc = pc + Rd-1;
                end
            end
            4'hd:begin      //branch
                pc = pc - Rd-1;
            end
            4'he:begin      //STUR
                addr = Rd;
                A <= 0;
                B <= Rx[Rn];
                alu_sel = 'b000;
                en_alu = 1;
                oe = 0;
                we = 1;
                #1
                we = 0;
                en_alu = 0;
            end
            4'hf:begin      //LDUR
                addr = Rd;
                we = 0;
                oe = 1;
                Rx[Rn] = bus;
                oe = 0;
            end
            default : A = 4'hz; //dummy code so it compiles
        endcase
    end

    always @(negedge clk)
    begin
        pc = pc + 1;
        #10
        instruction = tmp_mem;
    end

    always #500 clk = ~clk;

    //instruction opcode, rd, rn, rm

    initial begin
        clk = 0;
        {we, oe, en_alu, addr, a, en_imem} <= 0;
        for(i = 0; i < 16; i = i+1) begin
            Rx[i] = 0;
        end
        i = 0;
        #100
        pc = -1;
        #100
        $dumpfile("test.vcd");
        $dumpvars(0, clk, instruction, bus);
        $monitor("fib=%d",Rx[4]);
        
    end
endmodule

test.vcd
$date
	Mon Apr 25 19:07:34 2022
$end
$version
	Icarus Verilog
$end
$timescale
	1s
$end
$scope module CPU $end
$var reg 1 ! clk $end
$upscope $end
$scope module CPU $end
$var reg 16 " instruction [15:0] $end
$upscope $end
$scope module CPU $end
$var wire 16 # bus [15:0] $end
$upscope $end
$enddefinitions $end
#200
$dumpvars
bz #
bx "
0!
$end
#500
1!
#1000
0!
#1010
b1000000000001 "
#1500
b1 #
1!
#1501
bz #
#2000
0!
#2010
b1010000000000 "
#2500
b1 #
1!
#2501
bz #
#3000
0!
#3010
b100000000 "
#3500
b10 #
1!
#3501
bz #
#4000
0!
#4010
b1010000010000 "
#4500
b10 #
1!
#4501
bz #
#5000
0!
#5010
b1000010000 "
#5500
b11 #
1!
#5501
bz #
#6000
0!
#6010
b1010000100000 "
#6500
b11 #
1!
#6501
bz #
#7000
0!
#7010
b10010 "
#7500
b101 #
1!
#7501
bz #
#8000
0!
#8010
b1010000000000 "
#8500
b101 #
1!
#8501
bz #
#9000
0!
#9010
b100100000 "
#9500
b1000 #
1!
#9501
bz #
#10000
0!
#10010
b1010000010000 "
#10500
b1000 #
1!
#10501
bz #
#11000
0!
#11010
b1001100110001 "
#11500
b1 #
1!
#11501
bz #
#12000
0!
#12010
b1100001000110101 "
#12500
1!
#13000
0!
#13010
b1101100000000000 "
#13500
1!
#14000
0!
#14010
b1000010000 "
#14500
b1101 #
1!
#14501
bz #
#15000
0!
#15010
b1010000100000 "
#15500
b1101 #
1!
#15501
bz #
#16000
0!
#16010
b10010 "
#16500
b10101 #
1!
#16501
bz #
#17000
0!
#17010
b1010000000000 "
#17500
b10101 #
1!
#17501
bz #
#18000
0!
#18010
b100100000 "
#18500
b100010 #
1!
#18501
bz #
#19000
0!
#19010
b1010000010000 "
#19500
b100010 #
1!
#19501
bz #
#20000
0!
#20010
b1001100110001 "
#20500
b10 #
1!
#20501
bz #
#21000
0!
#21010
b1100001000110101 "
#21500
1!
#22000
0!
#22010
b1101100000000000 "
#22500
1!
#23000
0!
#23010
b1000010000 "
#23500
b110111 #
1!
#23501
bz #
#24000
0!
#24010
b1010000100000 "
#24500
b110111 #
1!
#24501
bz #
#25000
0!
#25010
b10010 "
#25500
b1011001 #
1!
#25501
bz #
#26000
0!
#26010
b1010000000000 "
#26500
b1011001 #
1!
#26501
bz #
#27000
0!
#27010
b100100000 "
#27500
b10010000 #
1!
#27501
bz #
#28000
0!
#28010
b1010000010000 "
#28500
b10010000 #
1!
#28501
bz #
#29000
0!
#29010
b1001100110001 "
#29500
b11 #
1!
#29501
bz #
#30000
0!
#30010
b1100001000110101 "
#30500
1!
#31000
0!
#31010
b1101100000000000 "
#31500
1!
#32000
0!
#32010
b1000010000 "
#32500
b11101001 #
1!
#32501
bz #
#33000
0!
#33010
b1010000100000 "
#33500
b11101001 #
1!
#33501
bz #
#34000
0!
#34010
b10010 "
#34500
b101111001 #
1!
#34501
bz #
#35000
0!
#35010
b1010000000000 "
#35500
b101111001 #
1!
#35501
bz #
#36000
0!
#36010
b100100000 "
#36500
b1001100010 #
1!
#36501
bz #
#37000
0!
#37010
b1010000010000 "
#37500
b1001100010 #
1!
#37501
bz #
#38000
0!
#38010
b1001100110001 "
#38500
b100 #
1!
#38501
bz #
#39000
0!
#39010
b1100001000110101 "
#39500
1!
#40000
0!
#40010
b1101100000000000 "
#40500
1!
#41000
0!
#41010
b1000010000 "
#41500
b1111011011 #
1!
#41501
bz #
#42000
0!
#42010
b1010000100000 "
#42500
b1111011011 #
1!
#42501
bz #
#43000
0!
#43010
b10010 "
#43500
b11000111101 #
1!
#43501
bz #
#44000
0!
#44010
b1010000000000 "
#44500
b11000111101 #
1!
#44501
bz #
#45000
0!
#45010
b100100000 "
#45500
b101000011000 #
1!
#45501
bz #
#46000
0!
#46010
b1010000010000 "
#46500
b101000011000 #
1!
#46501
bz #
#47000
0!
#47010
b1001100110001 "
#47500
b101 #
1!
#47501
bz #
#48000
0!
#48010
b1100001000110101 "
#48500
1!
#49000
0!
#49010
b1001000000000000 "
