imem.v
module IMem(
        output wire [15:0] data,
        input [3:0] a);

    reg [15:0] ram [0:31];

    initial $readmemh("fibb_recur.txt", ram); // load file with instructions onto memory

    assign data = ram[a];

endmodule

RAM.v
module RAM(
        inout [15:0] data,
        input [3:0] addr,
        input we, clk, oe
        );

    reg [15:0] ram [15:0];
    reg [15:0] tmp_data;

    always @ (posedge clk)
    begin
        if(we)
            ram[addr] <= data;  
        else
            tmp_data <= data;
    end

    assign data = oe & !we ? tmp_data : 'hz;

endmodule

buffer.v
module buffer(input [15:0] in, 
              input en, clk,
              output reg [15:0] out);
    
    always @(*) begin
        if(en)
            out <= in;
        else
            out <= 16'bx; // high impedence output to not interfere with bus
    end

endmodule

alu.v
module alu(
           input [15:0] A,B,  // ALU 8-bit Inputs                 
           input [2:0] ALU_Sel,// ALU Selection
           input shamt,
           output [15:0] ALU_Out, // ALU 8-bit Output
           output CarryOut // Carry Out Flag
    );
    reg [15:0] ALU_Result;
    wire [16:0] tmp;
    assign ALU_Out = ALU_Result; // ALU out
    assign tmp = {1'b0,A} + {1'b0,B};
    assign CarryOut = tmp[16]; // Carryout flag

    always @(*)
    begin
        case(ALU_Sel)
          3'b000: // Addition
           ALU_Result = A + B ; 
          3'b001: // Subtraction
           ALU_Result = A - B ;
          3'b010: //  Logical and 
           ALU_Result = A & B;
          3'b011: //  Logical or
           ALU_Result = A | B;
          3'b100: //  Logical xor 
           ALU_Result = A ^ B;
          3'b101: //  Logical nor
           ALU_Result = ~(A | B);
          3'b110: // Logical nand 
           ALU_Result = ~(A & B);
          3'b111: // LSL
           ALU_Result = A<<shamt;
          default: ALU_Result = A + B; 
        endcase
    end
endmodule

CPU.v
module CPU();

    //instruction 15-12 11-8 7-4 3-0

    reg [15:0] instruction, C;
    reg [15:0] A, B, zero;
    reg [15:0] Rx [15:0];
    reg [2:0] alu_sel;
    wire [15:0] bus;
    wire carryFlag;
    reg en_alu, en_imem, shamt;
    wire [3:0] Rn, Rd, Rm, opcode;
    reg clk;
    reg we, oe;
    reg [3:0] addr;
    reg [3:0] a, pc;
    integer i;

    assign opcode = instruction[15:12];
    assign Rd = instruction[11:8];
    assign Rn = instruction[7:4];
    assign Rm = instruction[3:0];

    wire [15:0] tmp_alu, tmp_mem;
    alu aluop(.A(A), .B(B), .ALU_Out(tmp_alu), .ALU_Sel(alu_sel), .CarryOut(carryFlag), .shamt(shamt));
    buffer aluBuff(.clk(clk), .en(en_alu), .in(tmp_alu), .out(bus));
    RAM data(.data(bus), .clk(clk), .we(we), .oe(oe), .addr(addr));
    IMem mem(.a(pc), .data(tmp_mem));
    
    always@(posedge clk)
    begin
        case(opcode)
            4'h0:begin      // ADD
                A <= Rx[Rn];
                B <= Rx[Rm];
                alu_sel = 3'b000;
                en_alu = 1'b1;
                #1
                Rx[Rd] = bus;
                en_alu = 1'b0;
            end
            4'h1:begin      // ADDI
                A <= Rx[Rn];
                B <= Rm;
                alu_sel = 3'b000;
                en_alu = 1'b1;
                #1
                Rx[Rd] = bus;
                en_alu = 1'b0;
            end
            4'h2:begin      // SUB
                A <= Rx[Rn];
                B <= Rx[Rm];
                alu_sel = 3'b001;
                en_alu = 1'b1;
                #1
                Rx[Rd] = bus;
                en_alu = 1'b0;
            end
            4'h3:begin      //SUBI
                A <= Rx[Rn];
                B <= Rm;
                alu_sel = 3'b001;
                en_alu = 1'b1;
                #1
                Rx[Rd] = bus;
                en_alu = 1'b0;
            end
            4'h4:begin      //AND
                A <= Rx[Rn];
                B <= Rx[Rm];
                alu_sel = 3'b010;
                en_alu = 1'b1;
                #1
                Rx[Rd] = bus;
                en_alu = 1'b0;
            end
            4'h5:begin      //OR
                A <= Rx[Rn];
                B <= Rx[Rm];
                alu_sel = 3'b011;
                en_alu = 1'b1;
                #1
                Rx[Rd] = bus;
                en_alu = 1'b0;
            end
            4'h6:begin      //XOR
                A <= Rx[Rn];
                B <= Rx[Rm];
                alu_sel = 3'b100;
                en_alu = 1'b1;
                #1
                Rx[Rd] = bus;
                en_alu = 1'b0;
            end
            4'h7:begin      //NOR
                A <= Rx[Rn];
                B <= Rx[Rm];
                alu_sel = 3'b101;
                en_alu = 1'b1;
                #1
                Rx[Rd] = bus;
                en_alu = 1'b0;
            end
            4'h8:begin      //NAND
                A <= Rx[Rn];
                B <= Rx[Rm];
                alu_sel = 3'b110;
                en_alu = 1'b1;
                #1
                Rx[Rd] = bus;
                en_alu = 1'b0;
            end
            4'h9: $finish;
            4'ha:begin      //LSL
                A <= Rx[Rn];
                shamt <= Rm;
                alu_sel = 3'b111;
                en_alu = 1'b1;
                #1
                Rx[Rd] = bus;
                en_alu = 1'b0;
            end
            4'hb:begin      //BL
                Rx[15] = pc + 1;
                pc = Rd-1;
            end
            4'hc:begin      //BEQ (to immediate)
                if(Rx[Rn] == Rm) begin
                    pc = Rd-1;
                end
            end
            4'hd:begin      //branch
                pc = Rx[Rd];
            end
            4'he:begin      //STUR because of the way the registers were implemented, I have to get them onto the bus using the alu
                addr = Rd;
                A <= 0;
                B <= Rx[Rn];
                alu_sel = 'b000;
                en_alu = 1;
                oe = 0;
                we = 1;
                #1
                we = 0;
                en_alu = 0;
            end
            4'hf:begin      //LDUR
                addr = Rd;
                we = 0;
                oe = 1;
                Rx[Rn] = bus;
                oe = 0;
            end
            default : A = 4'hz; //dummy code so it compiles
        endcase
    end

    always @(negedge clk)
    begin
        pc = pc + 1;
        #10
        instruction = tmp_mem;
    end

    always #500 clk = ~clk;

    //instruction opcode, rd, rn, rm

    initial begin
        clk = 0;
        {we, oe, en_alu, addr, a, en_imem, zero} <= 0;
        for(i = 0; i < 16; i = i+1) begin
            Rx[i] = 0;
        end
        i = 0;
        #100
        pc = -1;
        #100
        $dumpfile("test.vcd");
        $dumpvars(0, clk, instruction, bus);
        $monitor("fib=%d",Rx[1]);
        
    end
endmodule

test.vcd
$date
	Mon Apr 25 23:41:29 2022
$end
$version
	Icarus Verilog
$end
$timescale
	1s
$end
$scope module CPU $end
$var reg 1 ! clk $end
$upscope $end
$scope module CPU $end
$var reg 16 " instruction [15:0] $end
$upscope $end
$scope module CPU $end
$var wire 16 # bus [15:0] $end
$upscope $end
$enddefinitions $end
#200
$dumpvars
bz #
bx "
0!
$end
#500
1!
#1000
0!
#1010
b1001011101111 "
#1500
b1111 #
1!
#1501
bz #
#2000
0!
#2010
b1010001000100001 "
#2500
b11110 #
1!
#2501
bz #
#3000
0!
#3010
b1010001000100100 "
#3500
b11110 #
1!
#3501
bz #
#4000
0!
#4010
b1101010100011 "
#4500
b11 #
1!
#4501
bz #
#5000
0!
#5010
b1110000110100000 "
#5500
b11 #
1!
#5501
bz #
#6000
0!
#6010
b1000000000010 "
#6500
b10 #
1!
#6501
bz #
#7000
0!
#7010
b1000101010101010 "
#7500
b1111111111111100 #
1!
#7501
bz #
#8000
0!
#8010
b100000100001010 "
#8500
b0 #
1!
#8501
bz #
#9000
0!
#9010
b1011001000010010 "
#9500
1!
#10000
0!
#10010
b1010001000100100 "
#10500
b11110 #
1!
#10501
bz #
#11000
0!
#11010
b1101010100011 "
#11500
b1111111111111111 #
1!
#11501
bz #
#12000
0!
#12010
b1110000110100000 "
#12500
b1111111111111111 #
1!
#12501
bz #
#13000
0!
#13010
b1000000000010 "
#13500
b100 #
1!
#13501
bz #
#14000
0!
#14010
b1000101010101010 "
#14500
b0 #
1!
#14501
bz #
#15000
0!
#15010
b100000100001010 "
#15500
b0 #
1!
#15501
bz #
#16000
0!
#16010
b1011001000010010 "
#16500
1!
#17000
0!
#17010
b1010001000100100 "
#17500
b11110 #
1!
#17501
bz #
#18000
0!
#18010
b1101010100011 "
#18500
b11 #
1!
#18501
bz #
#19000
0!
#19010
b1110000110100000 "
#19500
b11 #
1!
#19501
bz #
#20000
0!
#20010
b1000000000010 "
#20500
b110 #
1!
#20501
bz #
#21000
0!
#21010
b1000101010101010 "
#21500
b1111111111111100 #
1!
#21501
bz #
#22000
0!
#22010
b100000100001010 "
#22500
b100 #
1!
#22501
bz #
#23000
0!
#23010
b1011001000010010 "
#23500
1!
#24000
0!
#24010
b1010001000100100 "
#24500
b11110 #
1!
#24501
bz #
#25000
0!
#25010
b1101010100011 "
#25500
b1111111111111111 #
1!
#25501
bz #
#26000
0!
#26010
b1110000110100000 "
#26500
b1111111111111111 #
1!
#26501
bz #
#27000
0!
#27010
b1000000000010 "
#27500
b1000 #
1!
#27501
bz #
#28000
0!
#28010
b1000101010101010 "
#28500
b0 #
1!
#28501
bz #
#29000
0!
#29010
b100000100001010 "
#29500
b0 #
1!
#29501
bz #
#30000
0!
#30010
b1011001000010010 "
#30500
1!
#31000
0!
#31010
b1010001000100100 "
#31500
b11110 #
1!
#31501
bz #
#32000
0!
#32010
b1101010100011 "
#32500
b11 #
1!
#32501
bz #
#33000
0!
#33010
b1110000110100000 "
#33500
b11 #
1!
#33501
bz #
#34000
0!
#34010
b1000000000010 "
#34500
b1010 #
1!
#34501
bz #
#35000
0!
#35010
b1000101010101010 "
#35500
b1111111111111100 #
1!
#35501
bz #
#36000
0!
#36010
b100000100001010 "
#36500
b1000 #
1!
#36501
bz #
#37000
0!
#37010
b1011001000010010 "
#37500
1!
#38000
0!
#38010
b1010001000100100 "
#38500
b11110 #
1!
#38501
bz #
#39000
0!
#39010
b1101010100011 "
#39500
b1111111111111111 #
1!
#39501
bz #
#40000
0!
#40010
b1110000110100000 "
#40500
b1111111111111111 #
1!
#40501
bz #
#41000
0!
#41010
b1000000000010 "
#41500
b1100 #
1!
#41501
bz #
#42000
0!
#42010
b1000101010101010 "
#42500
b0 #
1!
#42501
bz #
#43000
0!
#43010
b100000100001010 "
#43500
b0 #
1!
#43501
bz #
#44000
0!
#44010
b1011001000010010 "
#44500
1!
#45000
0!
#45010
b1010001000100100 "
#45500
b11110 #
1!
#45501
bz #
#46000
0!
#46010
b1101010100011 "
#46500
b11 #
1!
#46501
bz #
#47000
0!
#47010
b1110000110100000 "
#47500
b11 #
1!
#47501
bz #
#48000
0!
#48010
b1000000000010 "
#48500
b1110 #
1!
#48501
bz #
#49000
0!
#49010
b1000101010101010 "
#49500
b1111111111111100 #
1!
#49501
bz #
#50000
0!
#50010
b100000100001010 "
#50500
b1100 #
1!
#50501
bz #
#51000
0!
#51010
b1011001000010010 "
#51500
1!
#52000
0!
#52010
b1010001000100100 "
#52500
b11110 #
1!
#52501
bz #
#53000
0!
#53010
b1101010100011 "
#53500
b1111111111111111 #
1!
#53501
bz #
#54000
0!
#54010
b1110000110100000 "
#54500
b1111111111111111 #
1!
#54501
bz #
#55000
0!
#55010
b1000000000010 "
#55500
b10000 #
1!
#55501
bz #
#56000
0!
#56010
b1000101010101010 "
#56500
b0 #
1!
#56501
bz #
#57000
0!
#57010
b100000100001010 "
#57500
b0 #
1!
#57501
bz #
#58000
0!
#58010
b1011001000010010 "
#58500
1!
#59000
0!
#59010
b1010001000100100 "
#59500
b11110 #
1!
#59501
bz #
#60000
0!
#60010
b1101010100011 "
#60500
b11 #
1!
#60501
bz #
#61000
0!
#61010
b1110000110100000 "
#61500
b11 #
1!
#61501
bz #
#62000
0!
#62010
b1000000000010 "
#62500
b10010 #
1!
#62501
bz #
#63000
0!
#63010
b1000101010101010 "
#63500
b1111111111111100 #
1!
#63501
bz #
#64000
0!
#64010
b100000100001010 "
#64500
b10000 #
1!
#64501
bz #
#65000
0!
#65010
b1011001000010010 "
#65500
1!
#66000
0!
#66010
b1010001000100100 "
#66500
b11110 #
1!
#66501
bz #
#67000
0!
#67010
b1101010100011 "
#67500
b1111111111111111 #
1!
#67501
bz #
#68000
0!
#68010
b1110000110100000 "
#68500
b1111111111111111 #
1!
#68501
bz #
#69000
0!
#69010
b1000000000010 "
#69500
b10100 #
1!
#69501
bz #
#70000
0!
#70010
b1000101010101010 "
#70500
b0 #
1!
#70501
bz #
#71000
0!
#71010
b100000100001010 "
#71500
b0 #
1!
#71501
bz #
#72000
0!
#72010
b1011001000010010 "
#72500
1!
#73000
0!
#73010
b1010001000100100 "
#73500
b11110 #
1!
#73501
bz #
#74000
0!
#74010
b1101010100011 "
#74500
b11 #
1!
#74501
bz #
#75000
0!
#75010
b1110000110100000 "
#75500
b11 #
1!
#75501
bz #
#76000
0!
#76010
b1000000000010 "
#76500
b10110 #
1!
#76501
bz #
#77000
0!
#77010
b1000101010101010 "
#77500
b1111111111111100 #
1!
#77501
bz #
#78000
0!
#78010
b100000100001010 "
#78500
b10100 #
1!
#78501
bz #
#79000
0!
#79010
b1011001000010010 "
#79500
1!
#80000
0!
#80010
b1010001000100100 "
#80500
b11110 #
1!
#80501
bz #
#81000
0!
#81010
b1101010100011 "
#81500
b1111111111111111 #
1!
#81501
bz #
#82000
0!
#82010
b1110000110100000 "
#82500
b1111111111111111 #
1!
#82501
bz #
#83000
0!
#83010
b1000000000010 "
#83500
b11000 #
1!
#83501
bz #
#84000
0!
#84010
b1000101010101010 "
#84500
b0 #
1!
#84501
bz #
#85000
0!
#85010
b100000100001010 "
#85500
b0 #
1!
#85501
bz #
#86000
0!
#86010
b1011001000010010 "
#86500
1!
#87000
0!
#87010
b1010001000100100 "
#87500
b11110 #
1!
#87501
bz #
#88000
0!
#88010
b1101010100011 "
#88500
b11 #
1!
#88501
bz #
#89000
0!
#89010
b1110000110100000 "
#89500
b11 #
1!
#89501
bz #
#90000
0!
#90010
b1000000000010 "
#90500
b11010 #
1!
#90501
bz #
#91000
0!
#91010
b1000101010101010 "
#91500
b1111111111111100 #
1!
#91501
bz #
#92000
0!
#92010
b100000100001010 "
#92500
b11000 #
1!
#92501
bz #
#93000
0!
#93010
b1011001000010010 "
#93500
1!
#94000
0!
#94010
b1010001000100100 "
#94500
b11110 #
1!
#94501
bz #
#95000
0!
#95010
b1101010100011 "
#95500
b1111111111111111 #
1!
#95501
bz #
#96000
0!
#96010
b1110000110100000 "
#96500
b1111111111111111 #
1!
#96501
bz #
#97000
0!
#97010
b1000000000010 "
#97500
b11100 #
1!
#97501
bz #
#98000
0!
#98010
b1000101010101010 "
#98500
b0 #
1!
#98501
bz #
#99000
0!
#99010
b100000100001010 "
#99500
b0 #
1!
#99501
bz #
#100000
0!
#100010
b1011001000010010 "
#100500
1!
#101000
0!
#101010
b1010001000100100 "
#101500
b11110 #
1!
#101501
bz #
#102000
0!
#102010
b1101010100011 "
#102500
b11 #
1!
#102501
bz #
#103000
0!
#103010
b1110000110100000 "
#103500
b11 #
1!
#103501
bz #
#104000
0!
#104010
b1000000000010 "
#104500
b11110 #
1!
#104501
bz #
#105000
0!
#105010
b1000101010101010 "
#105500
b1111111111111100 #
1!
#105501
bz #
#106000
0!
#106010
b100000100001010 "
#106500
b11100 #
1!
#106501
bz #
#107000
0!
#107010
b1011001000010010 "
#107500
1!
#108000
0!
#108010
b1010001000100100 "
#108500
b11110 #
1!
#108501
bz #
#109000
0!
#109010
b1101010100011 "
#109500
b1111111111111111 #
1!
#109501
bz #
#110000
0!
#110010
b1110000110100000 "
#110500
b1111111111111111 #
1!
#110501
bz #
#111000
0!
#111010
b1000000000010 "
#111500
b100000 #
1!
#111501
bz #
#112000
0!
#112010
b1000101010101010 "
#112500
b0 #
1!
#112501
bz #
#113000
0!
#113010
b100000100001010 "
#113500
b0 #
1!
#113501
bz #
#114000
0!
#114010
b1011001000010010 "
#114500
1!
#115000
0!
#115010
b1010001000100100 "
#115500
b11110 #
1!
#115501
bz #
#116000
0!
#116010
b1101010100011 "
#116500
b11 #
1!
#116501
bz #
#117000
0!
#117010
b1110000110100000 "
#117500
b11 #
1!
#117501
bz #
#118000
0!
#118010
b1000000000010 "
#118500
b100010 #
1!
#118501
bz #
#119000
0!
#119010
b1000101010101010 "
#119500
b1111111111111100 #
1!
#119501
bz #
#120000
0!
#120010
b100000100001010 "
#120500
b100000 #
1!
#120501
bz #
#121000
0!
#121010
b1011001000010010 "
#121500
1!
#122000
0!
#122010
b1010001000100100 "
#122500
b11110 #
1!
#122501
bz #
#123000
0!
#123010
b1101010100011 "
#123500
b1111111111111111 #
1!
#123501
bz #
#124000
0!
#124010
b1110000110100000 "
#124500
b1111111111111111 #
1!
#124501
bz #
#125000
0!
#125010
b1000000000010 "
#125500
b100100 #
1!
#125501
bz #
#126000
0!
#126010
b1000101010101010 "
#126500
b0 #
1!
#126501
bz #
#127000
0!
#127010
b100000100001010 "
#127500
b0 #
1!
#127501
bz #
#128000
0!
#128010
b1011001000010010 "
#128500
1!
#129000
0!
#129010
b1010001000100100 "
#129500
b11110 #
1!
#129501
bz #
#130000
0!
#130010
b1101010100011 "
#130500
b11 #
1!
#130501
bz #
#131000
0!
#131010
b1110000110100000 "
#131500
b11 #
1!
#131501
bz #
#132000
0!
#132010
b1000000000010 "
#132500
b100110 #
1!
#132501
bz #
#133000
0!
#133010
b1000101010101010 "
#133500
b1111111111111100 #
1!
#133501
bz #
#134000
0!
#134010
b100000100001010 "
#134500
b100100 #
1!
#134501
bz #
#135000
0!
#135010
b1011001000010010 "
#135500
1!
#136000
0!
#136010
b1010001000100100 "
#136500
b11110 #
1!
#136501
bz #
#137000
0!
#137010
b1101010100011 "
#137500
b1111111111111111 #
1!
#137501
bz #
#138000
0!
#138010
b1110000110100000 "
#138500
b1111111111111111 #
1!
#138501
bz #
#139000
0!
#139010
b1000000000010 "
#139500
b101000 #
1!
#139501
bz #
#140000
0!
#140010
b1000101010101010 "
#140500
b0 #
1!
#140501
bz #
#141000
0!
#141010
b100000100001010 "
#141500
b0 #
1!
#141501
bz #
#142000
0!
#142010
b1011001000010010 "
#142500
1!
#143000
0!
#143010
b1010001000100100 "
#143500
b11110 #
1!
#143501
bz #
#144000
0!
#144010
b1101010100011 "
#144500
b11 #
1!
#144501
bz #
#145000
0!
#145010
b1110000110100000 "
#145500
b11 #
1!
#145501
bz #
#146000
0!
#146010
b1000000000010 "
#146500
b101010 #
1!
#146501
bz #
#147000
0!
#147010
b1000101010101010 "
#147500
b1111111111111100 #
1!
#147501
bz #
#148000
0!
#148010
b100000100001010 "
#148500
b101000 #
1!
#148501
bz #
#149000
0!
#149010
b1011001000010010 "
#149500
1!
#150000
0!
#150010
b1010001000100100 "
#150500
b11110 #
1!
#150501
bz #
#151000
0!
#151010
b1101010100011 "
#151500
b1111111111111111 #
1!
#151501
bz #
#152000
0!
#152010
b1110000110100000 "
#152500
b1111111111111111 #
1!
#152501
bz #
#153000
0!
#153010
b1000000000010 "
#153500
b101100 #
1!
#153501
bz #
#154000
0!
#154010
b1000101010101010 "
#154500
b0 #
1!
#154501
bz #
#155000
0!
#155010
b100000100001010 "
#155500
b0 #
1!
#155501
bz #
#156000
0!
#156010
b1011001000010010 "
#156500
1!
#157000
0!
#157010
b1010001000100100 "
#157500
b11110 #
1!
#157501
bz #
#158000
0!
#158010
b1101010100011 "
#158500
b11 #
1!
#158501
bz #
#159000
0!
#159010
b1110000110100000 "
#159500
b11 #
1!
#159501
bz #
#160000
0!
#160010
b1000000000010 "
#160500
b101110 #
1!
#160501
bz #
#161000
0!
#161010
b1000101010101010 "
#161500
b1111111111111100 #
1!
#161501
bz #
#162000
0!
#162010
b100000100001010 "
#162500
b101100 #
1!
#162501
bz #
#163000
0!
#163010
b1011001000010010 "
#163500
1!
#164000
0!
#164010
b1010001000100100 "
#164500
b11110 #
1!
#164501
bz #
#165000
0!
#165010
b1101010100011 "
#165500
b1111111111111111 #
1!
#165501
bz #
#166000
0!
#166010
b1110000110100000 "
#166500
b1111111111111111 #
1!
#166501
bz #
#167000
0!
#167010
b1000000000010 "
#167500
b110000 #
1!
#167501
bz #
#168000
0!
#168010
b1000101010101010 "
#168500
b0 #
1!
#168501
bz #
#169000
0!
#169010
b100000100001010 "
#169500
b0 #
1!
#169501
bz #
#170000
0!
#170010
b1011001000010010 "
#170500
1!
#171000
0!
#171010
b1010001000100100 "
#171500
b11110 #
1!
#171501
bz #
#172000
0!
#172010
b1101010100011 "
#172500
b11 #
1!
#172501
bz #
#173000
0!
#173010
b1110000110100000 "
#173500
b11 #
1!
#173501
bz #
#174000
0!
#174010
b1000000000010 "
#174500
b110010 #
1!
#174501
bz #
#175000
0!
#175010
b1000101010101010 "
#175500
b1111111111111100 #
1!
#175501
bz #
#176000
0!
#176010
b100000100001010 "
#176500
b110000 #
1!
#176501
bz #
#177000
0!
#177010
b1011001000010010 "
#177500
1!
#178000
0!
#178010
b1010001000100100 "
#178500
b11110 #
1!
#178501
bz #
#179000
0!
#179010
b1101010100011 "
#179500
b1111111111111111 #
1!
#179501
bz #
#180000
0!
#180010
b1110000110100000 "
#180500
b1111111111111111 #
1!
#180501
bz #
#181000
0!
#181010
b1000000000010 "
#181500
b110100 #
1!
#181501
bz #
#182000
0!
#182010
b1000101010101010 "
#182500
b0 #
1!
#182501
bz #
#183000
0!
#183010
b100000100001010 "
#183500
b0 #
1!
#183501
bz #
#184000
0!
#184010
b1011001000010010 "
#184500
1!
#185000
0!
#185010
b1010001000100100 "
#185500
b11110 #
1!
#185501
bz #
#186000
0!
#186010
b1101010100011 "
#186500
b11 #
1!
#186501
bz #
#187000
0!
#187010
b1110000110100000 "
#187500
b11 #
1!
#187501
bz #
#188000
0!
#188010
b1000000000010 "
#188500
b110110 #
1!
#188501
bz #
#189000
0!
#189010
b1000101010101010 "
#189500
b1111111111111100 #
1!
#189501
bz #
#190000
0!
#190010
b100000100001010 "
#190500
b110100 #
1!
#190501
bz #
#191000
0!
#191010
b1011001000010010 "
#191500
1!
#192000
0!
#192010
b1010001000100100 "
#192500
b11110 #
1!
#192501
bz #
#193000
0!
#193010
b1101010100011 "
#193500
b1111111111111111 #
1!
#193501
bz #
#194000
0!
#194010
b1110000110100000 "
#194500
b1111111111111111 #
1!
#194501
bz #
#195000
0!
#195010
b1000000000010 "
#195500
b111000 #
1!
#195501
bz #
#196000
0!
#196010
b1000101010101010 "
#196500
b0 #
1!
#196501
bz #
#197000
0!
#197010
b100000100001010 "
#197500
b0 #
1!
#197501
bz #
#198000
0!
#198010
b1011001000010010 "
#198500
1!
#199000
0!
#199010
b1010001000100100 "
#199500
b11110 #
1!
#199501
bz #
#200000
0!
#200010
b1101010100011 "
#200500
b11 #
1!
#200501
bz #
#201000
0!
#201010
b1110000110100000 "
#201500
b11 #
1!
#201501
bz #
#202000
0!
#202010
b1000000000010 "
#202500
b111010 #
1!
#202501
bz #
#203000
0!
#203010
b1000101010101010 "
#203500
b1111111111111100 #
1!
#203501
bz #
#204000
0!
#204010
b100000100001010 "
#204500
b111000 #
1!
#204501
bz #
#205000
0!
#205010
b1011001000010010 "
#205500
1!
#206000
0!
#206010
b1010001000100100 "
#206500
b11110 #
1!
#206501
bz #
#207000
0!
#207010
b1101010100011 "
#207500
b1111111111111111 #
1!
#207501
bz #
#208000
0!
#208010
b1110000110100000 "
#208500
b1111111111111111 #
1!
#208501
bz #
#209000
0!
#209010
b1000000000010 "
#209500
b111100 #
1!
#209501
bz #
#210000
0!
#210010
b1000101010101010 "
#210500
b0 #
1!
#210501
bz #
#211000
0!
#211010
b100000100001010 "
#211500
b0 #
1!
#211501
bz #
#212000
0!
#212010
b1011001000010010 "
#212500
1!
#213000
0!
#213010
b1010001000100100 "
#213500
b11110 #
1!
#213501
bz #
#214000
0!
#214010
b1101010100011 "
#214500
b11 #
1!
#214501
bz #
#215000
0!
#215010
b1110000110100000 "
#215500
b11 #
1!
#215501
bz #
#216000
0!
#216010
b1000000000010 "
#216500
b111110 #
1!
#216501
bz #
#217000
0!
#217010
b1000101010101010 "
#217500
b1111111111111100 #
1!
#217501
bz #
#218000
0!
#218010
b100000100001010 "
#218500
b111100 #
1!
#218501
bz #
#219000
0!
#219010
b1011001000010010 "
#219500
1!
#220000
0!
#220010
b1010001000100100 "
#220500
b11110 #
1!
#220501
bz #
#221000
0!
#221010
b1101010100011 "
#221500
b1111111111111111 #
1!
#221501
bz #
#222000
0!
#222010
b1110000110100000 "
#222500
b1111111111111111 #
1!
#222501
bz #
#223000
0!
#223010
b1000000000010 "
#223500
b1000000 #
1!
#223501
bz #
#224000
0!
#224010
b1000101010101010 "
#224500
b0 #
1!
#224501
bz #
#225000
0!
#225010
b100000100001010 "
#225500
b0 #
1!
#225501
bz #
#226000
0!
#226010
b1011001000010010 "
#226500
1!
#227000
0!
#227010
b1010001000100100 "
#227500
b11110 #
1!
#227501
bz #
#228000
0!
#228010
b1101010100011 "
#228500
b11 #
1!
#228501
bz #
#229000
0!
#229010
b1110000110100000 "
#229500
b11 #
1!
#229501
bz #
#230000
0!
#230010
b1000000000010 "
#230500
b1000010 #
1!
#230501
bz #
#231000
0!
#231010
b1000101010101010 "
#231500
b1111111111111100 #
1!
#231501
bz #
#232000
0!
#232010
b100000100001010 "
#232500
b1000000 #
1!
#232501
bz #
#233000
0!
#233010
b1011001000010010 "
#233500
1!
#234000
0!
#234010
b1010001000100100 "
#234500
b11110 #
1!
#234501
bz #
#235000
0!
#235010
b1101010100011 "
#235500
b1111111111111111 #
1!
#235501
bz #
#236000
0!
#236010
b1110000110100000 "
#236500
b1111111111111111 #
1!
#236501
bz #
#237000
0!
#237010
b1000000000010 "
#237500
b1000100 #
1!
#237501
bz #
#238000
0!
#238010
b1000101010101010 "
#238500
b0 #
1!
#238501
bz #
#239000
0!
#239010
b100000100001010 "
#239500
b0 #
1!
#239501
bz #
#240000
0!
#240010
b1011001000010010 "
#240500
1!
#241000
0!
#241010
b1010001000100100 "
#241500
b11110 #
1!
#241501
bz #
#242000
0!
#242010
b1101010100011 "
#242500
b11 #
1!
#242501
bz #
#243000
0!
#243010
b1110000110100000 "
#243500
b11 #
1!
#243501
bz #
#244000
0!
#244010
b1000000000010 "
#244500
b1000110 #
1!
#244501
bz #
#245000
0!
#245010
b1000101010101010 "
#245500
b1111111111111100 #
1!
#245501
bz #
#246000
0!
#246010
b100000100001010 "
#246500
b1000100 #
1!
#246501
bz #
#247000
0!
#247010
b1011001000010010 "
#247500
1!
#248000
0!
#248010
b1010001000100100 "
#248500
b11110 #
1!
#248501
bz #
#249000
0!
#249010
b1101010100011 "
#249500
b1111111111111111 #
1!
#249501
bz #
#250000
0!
#250010
b1110000110100000 "
#250500
b1111111111111111 #
1!
#250501
bz #
#251000
0!
#251010
b1000000000010 "
#251500
b1001000 #
1!
#251501
bz #
#252000
0!
#252010
b1000101010101010 "
#252500
b0 #
1!
#252501
bz #
#253000
0!
#253010
b100000100001010 "
#253500
b0 #
1!
#253501
bz #
#254000
0!
#254010
b1011001000010010 "
#254500
1!
#255000
0!
#255010
b1010001000100100 "
#255500
b11110 #
1!
#255501
bz #
#256000
0!
#256010
b1101010100011 "
#256500
b11 #
1!
#256501
bz #
#257000
0!
#257010
b1110000110100000 "
#257500
b11 #
1!
#257501
bz #
#258000
0!
#258010
b1000000000010 "
#258500
b1001010 #
1!
#258501
bz #
#259000
0!
#259010
b1000101010101010 "
#259500
b1111111111111100 #
1!
#259501
bz #
#260000
0!
#260010
b100000100001010 "
#260500
b1001000 #
1!
#260501
bz #
#261000
0!
#261010
b1011001000010010 "
#261500
1!
#262000
0!
#262010
b1010001000100100 "
#262500
b11110 #
1!
#262501
bz #
#263000
0!
#263010
b1101010100011 "
#263500
b1111111111111111 #
1!
#263501
bz #
#264000
0!
#264010
b1110000110100000 "
#264500
b1111111111111111 #
1!
#264501
bz #
#265000
0!
#265010
b1000000000010 "
#265500
b1001100 #
1!
#265501
bz #
#266000
0!
#266010
b1000101010101010 "
#266500
b0 #
1!
#266501
bz #
#267000
0!
#267010
b100000100001010 "
#267500
b0 #
1!
#267501
bz #
#268000
0!
#268010
b1011001000010010 "
#268500
1!
#269000
0!
#269010
b1010001000100100 "
#269500
b11110 #
1!
#269501
bz #
#270000
0!
#270010
b1101010100011 "
#270500
b11 #
1!
#270501
bz #
#271000
0!
#271010
b1110000110100000 "
#271500
b11 #
1!
#271501
bz #
#272000
0!
#272010
b1000000000010 "
#272500
b1001110 #
1!
#272501
bz #
#273000
0!
#273010
b1000101010101010 "
#273500
b1111111111111100 #
1!
#273501
bz #
#274000
0!
#274010
b100000100001010 "
#274500
b1001100 #
1!
#274501
bz #
#275000
0!
#275010
b1011001000010010 "
#275500
1!
#276000
0!
#276010
b1010001000100100 "
#276500
b11110 #
1!
#276501
bz #
#277000
0!
#277010
b1101010100011 "
#277500
b1111111111111111 #
1!
#277501
bz #
#278000
0!
#278010
b1110000110100000 "
#278500
b1111111111111111 #
1!
#278501
bz #
#279000
0!
#279010
b1000000000010 "
#279500
b1010000 #
1!
#279501
bz #
#280000
0!
#280010
b1000101010101010 "
#280500
b0 #
1!
#280501
bz #
#281000
0!
#281010
b100000100001010 "
#281500
b0 #
1!
#281501
bz #
#282000
0!
#282010
b1011001000010010 "
#282500
1!
#283000
0!
#283010
b1010001000100100 "
#283500
b11110 #
1!
#283501
bz #
#284000
0!
#284010
b1101010100011 "
#284500
b11 #
1!
#284501
bz #
#285000
0!
#285010
b1110000110100000 "
#285500
b11 #
1!
#285501
bz #
#286000
0!
#286010
b1000000000010 "
#286500
b1010010 #
1!
#286501
bz #
#287000
0!
#287010
b1000101010101010 "
#287500
b1111111111111100 #
1!
#287501
bz #
#288000
0!
#288010
b100000100001010 "
#288500
b1010000 #
1!
#288501
bz #
#289000
0!
#289010
b1011001000010010 "
#289500
1!
#290000
0!
#290010
b1010001000100100 "
#290500
b11110 #
1!
#290501
bz #
#291000
0!
#291010
b1101010100011 "
#291500
b1111111111111111 #
1!
#291501
bz #
#292000
0!
#292010
b1110000110100000 "
#292500
b1111111111111111 #
1!
#292501
bz #
#293000
0!
#293010
b1000000000010 "
#293500
b1010100 #
1!
#293501
bz #
#294000
0!
#294010
b1000101010101010 "
#294500
b0 #
1!
#294501
bz #
#295000
0!
