imem.v
module IMem(
        output wire [15:0] data,
        input [3:0] a);

    reg [15:0] ram [0:31];

    initial $readmemh("fibb_iter.txt", ram); // load file with instructions onto memory
    //initial $readmemh("I-type_test.txt", ram);

    assign data = ram[a];

endmodule

RAM.v
module RAM(
        inout [15:0] data,
        input [3:0] addr,
        input we, clk, oe
        );

    reg [15:0] ram [15:0];
    reg [15:0] tmp_data;

    always @ (posedge clk)
    begin
        if(we)
            ram[addr] <= data;  
        else
            tmp_data <= data;
    end

    assign data = oe & !we ? tmp_data : 'hz;

endmodule

buffer.v
module buffer(input [15:0] in, 
              input en, clk,
              output reg [15:0] out);
    
    always @(*) begin
        if(en)
            out <= in;
        else
            out <= 16'bx; // high impedence output to not interfere with bus
    end

endmodule

alu.v
module alu(
           input [15:0] A,B,  // ALU 8-bit Inputs                 
           input [2:0] ALU_Sel,// ALU Selection
           input shamt,
           output [15:0] ALU_Out, // ALU 8-bit Output
           output CarryOut // Carry Out Flag
    );
    reg [15:0] ALU_Result;
    wire [16:0] tmp;
    assign ALU_Out = ALU_Result; // ALU out
    assign tmp = {1'b0,A} + {1'b0,B};
    assign CarryOut = tmp[16]; // Carryout flag

    always @(*)
    begin
        case(ALU_Sel)
          3'b000: // Addition
           ALU_Result = A + B ; 
          3'b001: // Subtraction
           ALU_Result = A - B ;
          3'b010: //  Logical and 
           ALU_Result = A & B;
          3'b011: //  Logical or
           ALU_Result = A | B;
          3'b100: //  Logical xor 
           ALU_Result = A ^ B;
          3'b101: //  Logical nor
           ALU_Result = ~(A | B);
          3'b110: // Logical nand 
           ALU_Result = ~(A & B);
          3'b111: // LSL
           ALU_Result = A<<shamt;
          default: ALU_Result = A + B; 
        endcase
    end
endmodule

CPU.v
`timescale 1ns/1ps
module CPU();

    //instruction 15-12 11-8 7-4 3-0

    reg [15:0] instruction;
    reg [15:0] A, B, zero;
    reg [15:0] Rx [15:0];
    reg [2:0] alu_sel;
    reg [3:0] addr, shamt, a, pc;
    reg en_alu, en_imem, we, oe, clk;
    wire [15:0] bus, ins_bus;
    wire carryFlag;
    wire [3:0] Rn, Rd, Rm, opcode;
   
    integer i;

    assign opcode = instruction[15:12];
    assign Rd = instruction[11:8];
    assign Rn = instruction[7:4];
    assign Rm = instruction[3:0];

    wire [15:0] tmp_alu;
    alu aluop(.A(A), .B(B), .ALU_Out(tmp_alu), .ALU_Sel(alu_sel), .CarryOut(carryFlag), .shamt(shamt));
    buffer aluBuff(.clk(clk), .en(en_alu), .in(tmp_alu), .out(bus));
    RAM data(.data(bus), .clk(clk), .we(we), .oe(oe), .addr(addr));
    IMem mem(.a(pc), .data(ins_bus));
    
    always@(posedge clk)
    begin
        case(opcode)
            4'h0:begin      // ADD
                A <= Rx[Rn];
                B <= Rx[Rm];
                alu_sel = 3'b000;
                en_alu = 1'b1;
                #1
                Rx[Rd] = bus;
                en_alu = 1'b0;
            end
            4'h1:begin      // ADDI
                A <= Rx[Rn];
                B <= Rm;
                alu_sel = 3'b000;
                en_alu = 1'b1;
                #1
                Rx[Rd] = bus;
                en_alu = 1'b0;
            end
            4'h2:begin      // SUB
                A <= Rx[Rn];
                B <= Rx[Rm];
                alu_sel = 3'b001;
                en_alu = 1'b1;
                #1
                Rx[Rd] = bus;
                en_alu = 1'b0;
            end
            4'h3:begin      //SUBI
                A <= Rx[Rn];
                B <= Rm;
                alu_sel = 3'b001;
                en_alu = 1'b1;
                #1
                Rx[Rd] = bus;
                en_alu = 1'b0;
            end
            4'h4:begin      //AND
                A <= Rx[Rn];
                B <= Rx[Rm];
                alu_sel = 3'b010;
                en_alu = 1'b1;
                #1
                Rx[Rd] = bus;
                en_alu = 1'b0;
            end
            4'h5:begin      //OR
                A <= Rx[Rn];
                B <= Rx[Rm];
                alu_sel = 3'b011;
                en_alu = 1'b1;
                #1
                Rx[Rd] = bus;
                en_alu = 1'b0;
            end
            4'h6:begin      //XOR
                A <= Rx[Rn];
                B <= Rx[Rm];
                alu_sel = 3'b100;
                en_alu = 1'b1;
                #1
                Rx[Rd] = bus;
                en_alu = 1'b0;
            end
            4'h7:begin      //Display
                $display("%d", Rx[Rd]);
            end
            4'h8:begin      //NAND
                A <= Rx[Rn];
                B <= Rx[Rm];
                alu_sel = 3'b110;
                en_alu = 1'b1;
                #1
                Rx[Rd] = bus;
                en_alu = 1'b0;
            end
            4'h9: $finish;
            4'ha:begin      //LSL
                A <= Rx[Rn];
                shamt <= Rm;
                alu_sel = 3'b111;
                en_alu = 1'b1;
                #1
                Rx[Rd] = bus;
                en_alu = 1'b0;
            end
            4'hb:begin      //BL
                Rx[15] = pc + 1;
                pc = Rx[Rd]-1;
            end
            4'hc:begin      //BEQ (to immediate)
                if(Rx[Rn] == Rx[Rm]) begin
                    pc = Rx[Rd]-1;
                end
            end
            4'hd:begin      //branch to register
                pc = Rx[Rd]-1;
            end
            4'he:begin      //STUR because of the way the registers were implemented, I have to get them onto the bus using the alu
                addr = Rd;
                A <= 0;
                B <= Rx[Rn];
                alu_sel = 'b000;
                en_alu = 1;
                oe = 0;
                we = 1;
                #1
                we = 0;
                en_alu = 0;
            end
            4'hf:begin      //LDUR
                addr = Rd;
                we = 0;
                oe = 1;
                Rx[Rn] = bus;
                oe = 0;
            end
            default : A = 4'hz; //dummy code so it compiles
        endcase
    end

    always @(negedge clk)
    begin
        pc = pc + 1;
        #10
        instruction = ins_bus;
    end

    always #50 clk = ~clk;

    //instruction opcode, rd, rn, rm

    initial begin
        clk = 0;
        {we, oe, en_alu, addr, a, en_imem, zero} <= 0;
        for(i = 0; i < 16; i = i+1) begin
            Rx[i] = 0;
        end
        i = 0;
        pc = -1;
        #100
        $dumpfile("test.vcd");
        $dumpvars(0, clk, instruction, bus, tmp_alu, Rx[0], Rx[1], Rx[2], Rx[3]);
        //$monitor("%d",Rx[1]);
        
    end
endmodule

test.vcd
$date
	Thu Apr 28 16:10:42 2022
$end
$version
	Icarus Verilog
$end
$timescale
	1ps
$end
$scope module CPU $end
$var reg 1 ! clk $end
$upscope $end
$scope module CPU $end
$var reg 16 " instruction [15:0] $end
$upscope $end
$scope module CPU $end
$var wire 16 # bus [15:0] $end
$upscope $end
$scope module CPU $end
$var wire 16 $ tmp_alu [15:0] $end
$upscope $end
$scope module CPU $end
$var reg 16 % \Rx[0] [15:0] $end
$upscope $end
$scope module CPU $end
$var reg 16 & \Rx[1] [15:0] $end
$upscope $end
$scope module CPU $end
$var reg 16 ' \Rx[2] [15:0] $end
$upscope $end
$scope module CPU $end
$var reg 16 ( \Rx[3] [15:0] $end
$upscope $end
$enddefinitions $end
#100000
$dumpvars
b0 (
b0 '
b0 &
b0 %
b0 $
bx #
b1000011100000 "
0!
$end
#110000
b1000111100001 "
#150000
b1 $
b1 #
1!
#151000
bx #
b1 &
#200000
0!
#210000
b1010011101111 "
#250000
b1111 $
b1111 #
1!
#251000
bx #
#300000
0!
#310000
b1001111100001 "
#350000
b1 $
b1 #
1!
#351000
bx #
b1 (
#400000
0!
#410000
b1010111101100 "
#450000
b1100 $
b1100 #
1!
#451000
bx #
#500000
0!
#510000
b1011011100110 "
#550000
b110 $
b110 #
1!
#551000
bx #
#600000
0!
#610000
b1000010000 "
#650000
b1 $
b1 #
1!
#651000
bx #
b1 '
#700000
0!
#710000
b1000000010000 "
#750000
b1 #
1!
#751000
bx #
b1 %
#800000
0!
#810000
b1000100100000 "
#850000
b1 #
1!
#851000
bx #
b1 &
#900000
0!
#910000
b1001100110001 "
#950000
b10 $
b10 #
1!
#951000
bx #
b10 (
#1000000
0!
#1010000
b1100010100110100 "
#1050000
1!
#1100000
0!
#1110000
b1101011000000000 "
#1150000
1!
#1200000
0!
#1210000
b1000010000 "
#1250000
b10 #
1!
#1251000
bx #
b10 '
#1300000
0!
#1310000
b1000000010000 "
#1350000
b1 $
b1 #
1!
#1351000
bx #
b1 %
#1400000
0!
#1410000
b1000100100000 "
#1450000
b10 $
b10 #
1!
#1451000
bx #
b10 &
#1500000
0!
#1510000
b1001100110001 "
#1550000
b11 $
b11 #
1!
#1551000
bx #
b11 (
#1600000
0!
#1610000
b1100010100110100 "
#1650000
1!
#1700000
0!
#1710000
b1101011000000000 "
#1750000
1!
#1800000
0!
#1810000
b1000010000 "
#1850000
b11 #
1!
#1851000
bx #
b11 '
#1900000
0!
#1910000
b1000000010000 "
#1950000
b10 $
b10 #
1!
#1951000
bx #
b10 %
#2000000
0!
#2010000
b1000100100000 "
#2050000
b11 $
b11 #
1!
#2051000
bx #
b11 &
#2100000
0!
#2110000
b1001100110001 "
#2150000
b100 $
b100 #
1!
#2151000
bx #
b100 (
#2200000
0!
#2210000
b1100010100110100 "
#2250000
1!
#2300000
0!
#2310000
b1101011000000000 "
#2350000
1!
#2400000
0!
#2410000
b1000010000 "
#2450000
b101 $
b101 #
1!
#2451000
bx #
b101 '
#2500000
0!
#2510000
b1000000010000 "
#2550000
b11 $
b11 #
1!
#2551000
bx #
b11 %
#2600000
0!
#2610000
b1000100100000 "
#2650000
b101 $
b101 #
1!
#2651000
bx #
b101 &
#2700000
0!
#2710000
b1001100110001 "
#2750000
b101 #
1!
#2751000
bx #
b101 (
#2800000
0!
#2810000
b1100010100110100 "
#2850000
1!
#2900000
0!
#2910000
b1101011000000000 "
#2950000
1!
#3000000
0!
#3010000
b1000010000 "
#3050000
b1000 $
b1000 #
1!
#3051000
bx #
b1000 '
#3100000
0!
#3110000
b1000000010000 "
#3150000
b101 $
b101 #
1!
#3151000
bx #
b101 %
#3200000
0!
#3210000
b1000100100000 "
#3250000
b1000 $
b1000 #
1!
#3251000
bx #
b1000 &
#3300000
0!
#3310000
b1001100110001 "
#3350000
b110 $
b110 #
1!
#3351000
bx #
b110 (
#3400000
0!
#3410000
b1100010100110100 "
#3450000
1!
#3500000
0!
#3510000
b1101011000000000 "
#3550000
1!
#3600000
0!
#3610000
b1000010000 "
#3650000
b1101 $
b1101 #
1!
#3651000
bx #
b1101 '
#3700000
0!
#3710000
b1000000010000 "
#3750000
b1000 $
b1000 #
1!
#3751000
bx #
b1000 %
#3800000
0!
#3810000
b1000100100000 "
#3850000
b1101 $
b1101 #
1!
#3851000
bx #
b1101 &
#3900000
0!
#3910000
b1001100110001 "
#3950000
b111 $
b111 #
1!
#3951000
bx #
b111 (
#4000000
0!
#4010000
b1100010100110100 "
#4050000
1!
#4100000
0!
#4110000
b1101011000000000 "
#4150000
1!
#4200000
0!
#4210000
b1000010000 "
#4250000
b10101 $
b10101 #
1!
#4251000
bx #
b10101 '
#4300000
0!
#4310000
b1000000010000 "
#4350000
b1101 $
b1101 #
1!
#4351000
bx #
b1101 %
#4400000
0!
#4410000
b1000100100000 "
#4450000
b10101 $
b10101 #
1!
#4451000
bx #
b10101 &
#4500000
0!
#4510000
b1001100110001 "
#4550000
b1000 $
b1000 #
1!
#4551000
bx #
b1000 (
#4600000
0!
#4610000
b1100010100110100 "
#4650000
1!
#4700000
0!
#4710000
b1101011000000000 "
#4750000
1!
#4800000
0!
#4810000
b1000010000 "
#4850000
b100010 $
b100010 #
1!
#4851000
bx #
b100010 '
#4900000
0!
#4910000
b1000000010000 "
#4950000
b10101 $
b10101 #
1!
#4951000
bx #
b10101 %
#5000000
0!
#5010000
b1000100100000 "
#5050000
b100010 $
b100010 #
1!
#5051000
bx #
b100010 &
#5100000
0!
#5110000
b1001100110001 "
#5150000
b1001 $
b1001 #
1!
#5151000
bx #
b1001 (
#5200000
0!
#5210000
b1100010100110100 "
#5250000
1!
#5300000
0!
#5310000
b1101011000000000 "
#5350000
1!
#5400000
0!
#5410000
b1000010000 "
#5450000
b110111 $
b110111 #
1!
#5451000
bx #
b110111 '
#5500000
0!
#5510000
b1000000010000 "
#5550000
b100010 $
b100010 #
1!
#5551000
bx #
b100010 %
#5600000
0!
#5610000
b1000100100000 "
#5650000
b110111 $
b110111 #
1!
#5651000
bx #
b110111 &
#5700000
0!
#5710000
b1001100110001 "
#5750000
b1010 $
b1010 #
1!
#5751000
bx #
b1010 (
#5800000
0!
#5810000
b1100010100110100 "
#5850000
1!
#5900000
0!
#5910000
b1101011000000000 "
#5950000
1!
#6000000
0!
#6010000
b1000010000 "
#6050000
b1011001 $
b1011001 #
1!
#6051000
bx #
b1011001 '
#6100000
0!
#6110000
b1000000010000 "
#6150000
b110111 $
b110111 #
1!
#6151000
bx #
b110111 %
#6200000
0!
#6210000
b1000100100000 "
#6250000
b1011001 $
b1011001 #
1!
#6251000
bx #
b1011001 &
#6300000
0!
#6310000
b1001100110001 "
#6350000
b1011 $
b1011 #
1!
#6351000
bx #
b1011 (
#6400000
0!
#6410000
b1100010100110100 "
#6450000
1!
#6500000
0!
#6510000
b1101011000000000 "
#6550000
1!
#6600000
0!
#6610000
b1000010000 "
#6650000
b10010000 $
b10010000 #
1!
#6651000
bx #
b10010000 '
#6700000
0!
#6710000
b1000000010000 "
#6750000
b1011001 $
b1011001 #
1!
#6751000
bx #
b1011001 %
#6800000
0!
#6810000
b1000100100000 "
#6850000
b10010000 $
b10010000 #
1!
#6851000
bx #
b10010000 &
#6900000
0!
#6910000
b1001100110001 "
#6950000
b1100 $
b1100 #
1!
#6951000
bx #
b1100 (
#7000000
0!
#7010000
b1100010100110100 "
#7050000
1!
#7100000
0!
#7110000
b1101011000000000 "
#7150000
1!
#7200000
0!
#7210000
b1000010000 "
#7250000
b11101001 $
b11101001 #
1!
#7251000
bx #
b11101001 '
#7300000
0!
#7310000
b1000000010000 "
#7350000
b10010000 $
b10010000 #
1!
#7351000
bx #
b10010000 %
#7400000
0!
#7410000
b1000100100000 "
#7450000
b11101001 $
b11101001 #
1!
#7451000
bx #
b11101001 &
#7500000
0!
#7510000
b1001100110001 "
#7550000
b1101 $
b1101 #
1!
#7551000
bx #
b1101 (
#7600000
0!
#7610000
b1100010100110100 "
#7650000
1!
#7700000
0!
#7710000
b1101011000000000 "
#7750000
1!
#7800000
0!
#7810000
b1000010000 "
#7850000
b101111001 $
b101111001 #
1!
#7851000
bx #
b101111001 '
#7900000
0!
#7910000
b1000000010000 "
#7950000
b11101001 $
b11101001 #
1!
#7951000
bx #
b11101001 %
#8000000
0!
#8010000
b1000100100000 "
#8050000
b101111001 $
b101111001 #
1!
#8051000
bx #
b101111001 &
#8100000
0!
#8110000
b1001100110001 "
#8150000
b1110 $
b1110 #
1!
#8151000
bx #
b1110 (
#8200000
0!
#8210000
b1100010100110100 "
#8250000
1!
#8300000
0!
#8310000
b1101011000000000 "
#8350000
1!
#8400000
0!
#8410000
b1000010000 "
#8450000
b1001100010 $
b1001100010 #
1!
#8451000
bx #
b1001100010 '
#8500000
0!
#8510000
b1000000010000 "
#8550000
b101111001 $
b101111001 #
1!
#8551000
bx #
b101111001 %
#8600000
0!
#8610000
b1000100100000 "
#8650000
b1001100010 $
b1001100010 #
1!
#8651000
bx #
b1001100010 &
#8700000
0!
#8710000
b1001100110001 "
#8750000
b1111 $
b1111 #
1!
#8751000
bx #
b1111 (
#8800000
0!
#8810000
b1100010100110100 "
#8850000
1!
#8900000
0!
#8910000
b111000100000000 "
#8950000
1!
#9000000
0!
#9010000
b1001000000000000 "
